hiro/__init__.py
hiro/_version.py
hiro/core.py
hiro/errors.py
hiro/patches.py
hiro/utils.py
hiro/version.py
hiro-1.1.1.dist-info/LICENSE
hiro-1.1.1.dist-info/METADATA
hiro-1.1.1.dist-info/WHEEL
hiro-1.1.1.dist-info/top_level.txt
hiro-1.1.1.dist-info/RECORD
